excalc_py.py
excalc_py-0.0.4.dist-info/LICENSE
excalc_py-0.0.4.dist-info/WHEEL
excalc_py-0.0.4.dist-info/METADATA
excalc_py-0.0.4.dist-info/RECORD
